LICENSE
MANIFEST.in
Makefile
README
README.md
markdown-docs
setup.py
markdown_docs.egg-info/PKG-INFO
markdown_docs.egg-info/SOURCES.txt
markdown_docs.egg-info/dependency_links.txt
markdown_docs.egg-info/not-zip-safe
markdown_docs.egg-info/requires.txt
markdown_docs.egg-info/top_level.txt
markdowndocs/__init__.py
markdowndocs/__init__.pyc
markdowndocs/generator.py
markdowndocs/generator.pyc
markdowndocs/log_handler.py
markdowndocs/log_handler.pyc
markdowndocs/markdown_file.py
markdowndocs/markdown_file.pyc
markdowndocs/web_server.py
markdowndocs/web_server.pyc
markdowndocs/static/css/markdown-docs.css
markdowndocs/static/css/markdown.css
markdowndocs/static/js/jquery-1.9.1.min.js
markdowndocs/templates/index.html
markdowndocs/templates/markdown-template.html