Metadata-Version: 1.1
Name: markdown-docs
Version: 0.2.0
Summary: Documentation generator for Markdown projects
Home-page: http://sebdah.github.com/markdown-docs/
Author: Sebastian Dahlgren
Author-email: sebastian.dahlgren@gmail.com
License: Apache License, Version 2.0
Keywords: markdown documentation md mdown
Platform: Any
Classifier: Development Status :: 4 - Beta
Classifier: Environment :: Console
Classifier: License :: OSI Approved :: Apache Software License
Classifier: Operating System :: OS Independent
Classifier: Programming Language :: Python
